kolabpy/Kosispy.py
kolabpy/SASLogin.py
kolabpy/SASMagic.py
kolabpy/__init__.py
kolabpy/convert_code.py
kolabpy/p_domap.py
kolabpy-1.0.4.1.dist-info/METADATA
kolabpy-1.0.4.1.dist-info/WHEEL
kolabpy-1.0.4.1.dist-info/top_level.txt
kolabpy-1.0.4.1.dist-info/RECORD
