Metadata-Version: 2.4
Name: kolabpy
Version: 1.0.4.1
Summary: Contributor:te.park@snu.ac.kr,kkd8326@snu.ac.kr
Author: Kyungdong Kim
Author-email: kkd8326@snu.ac.kr
Classifier: Programming Language :: Python :: 3
Classifier: License :: OSI Approved :: MIT License
Classifier: Operating System :: OS Independent
Requires-Python: >=3.6
Requires-Dist: saspy
Requires-Dist: requests
Requires-Dist: pandas
Requires-Dist: geopandas
Requires-Dist: folium
Requires-Dist: ipython
Requires-Dist: pygments
Requires-Dist: beautifulsoup4
Dynamic: author
Dynamic: author-email
Dynamic: classifier
Dynamic: requires-dist
Dynamic: requires-python
Dynamic: summary
